paperchaser/__init__.py
paperchaser/cli.py
paperchaser/core.py
paperchaser-0.1.1.dist-info/METADATA
paperchaser-0.1.1.dist-info/WHEEL
paperchaser-0.1.1.dist-info/entry_points.txt
paperchaser-0.1.1.dist-info/top_level.txt
paperchaser-0.1.1.dist-info/RECORD
