Metadata-Version: 2.2
Name: paperchaser
Version: 0.1.1
Summary: A tool for downloading academic paper references
Author-email: semiquant <Jason.Limberis@ucsf.edu>
License: MIT
Project-URL: Homepage, https://www.SemiQuant.com
Classifier: Programming Language :: Python :: 3
Classifier: License :: OSI Approved :: MIT License
Classifier: Operating System :: OS Independent
Requires-Python: >=3.6
Requires-Dist: requests
Requires-Dist: beautifulsoup4
Requires-Dist: click
Requires-Dist: tabulate
Requires-Dist: tqdm
Requires-Dist: scholarly
Requires-Dist: crossrefapi
Requires-Dist: PyPDF2
Requires-Dist: pdf-renamer
